osrs_api/__init__.py
osrs_api/const.py
osrs_api/grandexchange.py
osrs_api/hiscores.py
osrs_api/item.py
osrs_api/items_osrs.json
osrs_api/priceinfo.py
osrs_api/pricetrend.py
osrs_api/skill.py
python_osrsapi-0.0.5.dist-info/LICENSE
python_osrsapi-0.0.5.dist-info/METADATA
python_osrsapi-0.0.5.dist-info/WHEEL
python_osrsapi-0.0.5.dist-info/top_level.txt
python_osrsapi-0.0.5.dist-info/RECORD
