Metadata-Version: 2.1
Name: python-osrsapi
Version: 0.0.5
Summary: Oldschool Runescape API wrapper
Home-page: https://github.com/Chasesc/OSRS-API-Wrapper
Author: Chasesc
Project-URL: Bug Reports, https://github.com/Chasesc/OSRS-API-Wrapper/issues
Project-URL: Source, https://github.com/Chasesc/OSRS-API-Wrapper/
Keywords: osrs,runescape,jagex,api,grandexchange,hiscores
Classifier: Development Status :: 3 - Alpha
Classifier: Intended Audience :: Developers
Classifier: Programming Language :: Python :: 3
Classifier: License :: OSI Approved :: MIT License
Classifier: Operating System :: OS Independent
Requires-Python: >=3.6
License-File: LICENSE
